{
  "config": {
    "total_steps": 500000,
    "rollout_steps": 2048,
    "lr": 0.0003,
    "gamma": 0.99,
    "lam": 0.95,
    "clip_eps": 0.2,
    "vf_coef": 0.5,
    "ent_coef": 0.01,
    "n_epochs": 4,
    "log_interval": 10,
    "save_interval": 50000,
    "save_dir": "checkpoints"
  },
  "validation": [
    {
      "finish_rate": 1.0,
      "fall_rate": 0.0,
      "avg_gates_passed": 8.0,
      "avg_gates_missed": 0.0,
      "perfect_run_rate": 1.0,
      "avg_score": 480.0,
      "avg_reward": 943.601588186519,
      "step": 51200,
      "seed": 0
    },
    {
      "finish_rate": 1.0,
      "fall_rate": 0.0,
      "avg_gates_passed": 8.0,
      "avg_gates_missed": 0.0,
      "perfect_run_rate": 1.0,
      "avg_score": 480.0,
      "avg_reward": 943.6113494311548,
      "step": 100352,
      "seed": 0
    },
    {
      "finish_rate": 1.0,
      "fall_rate": 0.0,
      "avg_gates_passed": 8.0,
      "avg_gates_missed": 0.0,
      "perfect_run_rate": 1.0,
      "avg_score": 480.0,
      "avg_reward": 943.5710464008778,
      "step": 151552,
      "seed": 0
    },
    {
      "finish_rate": 1.0,
      "fall_rate": 0.0,
      "avg_gates_passed": 8.0,
      "avg_gates_missed": 0.0,
      "perfect_run_rate": 1.0,
      "avg_score": 480.0,
      "avg_reward": 943.6154541841594,
      "step": 200704,
      "seed": 0
    },
    {
      "finish_rate": 1.0,
      "fall_rate": 0.0,
      "avg_gates_passed": 8.0,
      "avg_gates_missed": 0.0,
      "perfect_run_rate": 1.0,
      "avg_score": 480.0,
      "avg_reward": 943.5845563016734,
      "step": 251904,
      "seed": 0
    },
    {
      "finish_rate": 1.0,
      "fall_rate": 0.0,
      "avg_gates_passed": 8.0,
      "avg_gates_missed": 0.0,
      "perfect_run_rate": 1.0,
      "avg_score": 480.0,
      "avg_reward": 943.6039580096765,
      "step": 301056,
      "seed": 0
    },
    {
      "finish_rate": 1.0,
      "fall_rate": 0.0,
      "avg_gates_passed": 8.0,
      "avg_gates_missed": 0.0,
      "perfect_run_rate": 1.0,
      "avg_score": 480.0,
      "avg_reward": 943.6156024352271,
      "step": 350208,
      "seed": 0
    },
    {
      "finish_rate": 1.0,
      "fall_rate": 0.0,
      "avg_gates_passed": 8.0,
      "avg_gates_missed": 0.0,
      "perfect_run_rate": 1.0,
      "avg_score": 480.0,
      "avg_reward": 943.5238112906287,
      "step": 401408,
      "seed": 0
    },
    {
      "finish_rate": 1.0,
      "fall_rate": 0.0,
      "avg_gates_passed": 8.0,
      "avg_gates_missed": 0.0,
      "perfect_run_rate": 1.0,
      "avg_score": 480.0,
      "avg_reward": 943.61314696508,
      "step": 450560,
      "seed": 0
    },
    {
      "finish_rate": 1.0,
      "fall_rate": 0.0,
      "avg_gates_passed": 8.0,
      "avg_gates_missed": 0.0,
      "perfect_run_rate": 1.0,
      "avg_score": 480.0,
      "avg_reward": 943.6178073634534,
      "step": 501760,
      "seed": 0
    },
    {
      "finish_rate": 1.0,
      "fall_rate": 0.0,
      "avg_gates_passed": 8.0,
      "avg_gates_missed": 0.0,
      "perfect_run_rate": 1.0,
      "avg_score": 480.0,
      "avg_reward": 943.6161169383502,
      "step": 501760,
      "seed": 0
    }
  ]
}